ansys/tools/meilisearch/__init__.py
ansys/tools/meilisearch/__main__.py
ansys/tools/meilisearch/all_doc_indexer.py
ansys/tools/meilisearch/cli.py
ansys/tools/meilisearch/client.py
ansys/tools/meilisearch/create_indexes.py
ansys/tools/meilisearch/get_pages.py
ansys/tools/meilisearch/scraper.py
ansys/tools/meilisearch/server.py
ansys/tools/meilisearch/utils.py
ansys/tools/meilisearch/templates/__init__.py
ansys/tools/meilisearch/templates/default.json
ansys/tools/meilisearch/templates/sphinx_pydata.json
ansys/tools/meilisearch/templates/utils.py
pymeilisearch-0.3.2.dist-info/entry_points.txt
pymeilisearch-0.3.2.dist-info/LICENSE
pymeilisearch-0.3.2.dist-info/WHEEL
pymeilisearch-0.3.2.dist-info/METADATA
pymeilisearch-0.3.2.dist-info/RECORD
