Metadata-Version: 2.1
Name: pymeilisearch
Version: 0.3.2
Summary:  A Python library for effortless indexing and searching of documentation using MeiliSearch.
Author-email: "ANSYS, Inc." <pyansys.core@ansys.com>
Maintainer-email: PyAnsys Core Team <pyansys.core@ansys.com>
Requires-Python: >=3.9,<4
Classifier: Development Status :: 4 - Beta
Classifier: Programming Language :: Python :: 3
Classifier: License :: OSI Approved :: MIT License
Classifier: Operating System :: OS Independent
Requires-Dist: importlib-metadata>=4.0
Requires-Dist: PyGithub>=1.58.0
Requires-Dist: jinja2>=3.1.2
Requires-Dist: meilisearch>=0.24.0
Requires-Dist: click>=8
Requires-Dist: pymeilisearch-scraper>=0.2.3,<3
Requires-Dist: pyOpenSSL>=23.2.0
Requires-Dist: cryptography>=41.0.4
Requires-Dist: ansys-sphinx-theme==0.16.2 ; extra == "doc"
Requires-Dist: numpydoc==1.7.0 ; extra == "doc"
Requires-Dist: Sphinx==6.2.1 ; extra == "doc"
Requires-Dist: sphinx-design==0.6.0 ; extra == "doc"
Requires-Dist: sphinx-jinja==2.0.2 ; extra == "doc"
Requires-Dist: sphinx-autoapi==3.1.1 ; extra == "doc"
Requires-Dist: sphinx-copybutton==0.5.2 ; extra == "doc"
Requires-Dist: sphinx-notfound-page==1.0.2 ; extra == "doc"
Requires-Dist: sphinx-jinja==2.0.2 ; extra == "doc"
Requires-Dist: pytest==8.2.1 ; extra == "tests"
Requires-Dist: pytest-cov==5.0.0 ; extra == "tests"
Requires-Dist: docker==7.1.0 ; extra == "tests"
Project-URL: Discussions, https://github.com/ansys/pymeilisearch/discussions
Project-URL: Documentation, https://pymeilisearch.docs.ansys.com
Project-URL: Homepage, https://github.com/ansys/pymeilisearch
Project-URL: Releases, https://github.com/ansys/pymeilisearch/releases
Project-URL: Source, https://github.com/ansys/pymeilisearch
Project-URL: Tracker, https://github.com/ansys/pymeilisearch/issues
Provides-Extra: doc
Provides-Extra: tests
